workwerobot/__init__.py
workwerobot/client.py
workwerobot/config.py
workwerobot/exceptions.py
workwerobot/logger.py
workwerobot/parser.py
workwerobot/pay.py
workwerobot/replies.py
workwerobot/robot.py
workwerobot/testing.py
workwerobot/utils.py
workwerobot/contrib/__init__.py
workwerobot/contrib/bottle.py
workwerobot/contrib/django.py
workwerobot/contrib/error.html
workwerobot/contrib/flask.py
workwerobot/contrib/tornado.py
workwerobot/crypto/__init__.py
workwerobot/crypto/exceptions.py
workwerobot/crypto/pkcs7.py
workwerobot/messages/__init__.py
workwerobot/messages/base.py
workwerobot/messages/entries.py
workwerobot/messages/events.py
workwerobot/messages/messages.py
workwerobot/session/__init__.py
workwerobot/session/filestorage.py
workwerobot/session/mongodbstorage.py
workwerobot/session/mysqlstorage.py
workwerobot/session/postgresqlstorage.py
workwerobot/session/redisstorage.py
workwerobot/session/saekvstorage.py
workwerobot/session/sqlitestorage.py
WorkWeRoBot-1.9.2.dist-info/METADATA
WorkWeRoBot-1.9.2.dist-info/WHEEL
WorkWeRoBot-1.9.2.dist-info/top_level.txt
WorkWeRoBot-1.9.2.dist-info/RECORD
