Metadata-Version: 2.1
Name: WorkWeRoBot
Version: 1.9.2
Summary: WeRoBot: writing WeChat Offical Account Robots with fun
Home-page: https://github.com/pppwaw/WorkWeRoBot
Author: pppwaw
Author-email: 2504454577@qq.com
License: MIT License
Keywords: workwechat workweixin workwerobot
Platform: UNKNOWN
Classifier: Development Status :: 4 - Beta
Classifier: License :: OSI Approved :: MIT License
Classifier: Operating System :: MacOS
Classifier: Operating System :: POSIX
Classifier: Operating System :: POSIX :: Linux
Classifier: Programming Language :: Python :: 3.4
Classifier: Programming Language :: Python :: 3.5
Classifier: Programming Language :: Python :: 3.6
Classifier: Programming Language :: Python :: 3.7
Classifier: Programming Language :: Python :: Implementation :: CPython
Classifier: Programming Language :: Python :: Implementation :: PyPy
Classifier: Intended Audience :: Developers
Classifier: Topic :: Software Development :: Libraries
Classifier: Topic :: Software Development :: Libraries :: Python Modules
Classifier: Topic :: Utilities
Requires-Dist: setuptools
Requires-Dist: xmltodict
Requires-Dist: requests
Requires-Dist: cryptography
Requires-Dist: six
Requires-Dist: bottle
Provides-Extra: crypto
Requires-Dist: cryptography ; extra == 'crypto'
